rfgb/__init__.py
rfgb/__main__.py
rfgb/_metadata.py
rfgb/boosting.py
rfgb/logic.py
rfgb/tree.py
rfgb/utils.py
rfgb/cmd/__init__.py
rfgb/cmd/init.py
rfgb/cmd/learn.py
rfgb/rdn/__init__.py
rfgb/rdn/infer.py
rfgb/rdn/learn.py
rfgb/tests/__init__.py
rfgb/tests/tests.py
rfgb/tests/rfgbtests/__init__.py
rfgb/tests/rfgbtests/test_boosting.py
rfgb/tests/rfgbtests/test_cmd.py
rfgb/tests/rfgbtests/test_logic.py
rfgb/tests/rfgbtests/test_tree.py
rfgb/tests/rfgbtests/test_utils.py
rfgb-0.3.1.dist-info/LICENSE
rfgb-0.3.1.dist-info/METADATA
rfgb-0.3.1.dist-info/WHEEL
rfgb-0.3.1.dist-info/entry_points.txt
rfgb-0.3.1.dist-info/top_level.txt
rfgb-0.3.1.dist-info/RECORD
