Metadata-Version: 2.1
Name: rfgb
Version: 0.3.1
Summary: Relational Functional Gradient Boosting in Python.
Home-page: UNKNOWN
Author: Alexander L. Hayes
Author-email: hayesall@iu.edu
License: GNU General Public License v3.0 (GPLv3)
Project-URL: Source Code, https://github.com/hayesall/rfgb
Project-URL: Bug Tracker, https://github.com/hayesall/rfgb/issues
Project-URL: Documentation, https://rfgb.readthedocs.io/en/latest/
Keywords: relational-learning
Platform: UNKNOWN
Classifier: Development Status :: 3 - Alpha
Classifier: License :: OSI Approved :: GNU General Public License v3 (GPLv3)
Classifier: Intended Audience :: Science/Research
Classifier: Programming Language :: Python :: 3.5
Classifier: Programming Language :: Python :: 3.6
Classifier: Programming Language :: Python :: 3.7
